f5cli/__init__.py
f5cli/cli.py
f5cli/constants.py
f5cli/commands/__init__.py
f5cli/commands/cmd_bigip/__init__.py
f5cli/commands/cmd_bigip/extension_operations.py
f5cli/commands/cmd_config/__init__.py
f5cli/commands/cmd_cs/__init__.py
f5cli/commands/cmd_login/__init__.py
f5cli/config/__init__.py
f5cli/config/auth.py
f5cli/config/core.py
f5cli/config/telemetry.py
f5cli/docs/__init__.py
f5cli/docs/help.yaml
f5cli/docs/utils.py
f5cli/utils/__init__.py
f5cli/utils/core.py
f5_cli-0.9.2.dist-info/LICENSE
f5_cli-0.9.2.dist-info/METADATA
f5_cli-0.9.2.dist-info/WHEEL
f5_cli-0.9.2.dist-info/entry_points.txt
f5_cli-0.9.2.dist-info/top_level.txt
f5_cli-0.9.2.dist-info/RECORD
