Metadata-Version: 2.1
Name: f5-cli
Version: 0.9.2
Summary: F5 CLI
Home-page: UNKNOWN
Author: F5 Ecosystems Group
Author-email: solutionsfeedback@f5.com
License: Apache License 2.0
Platform: UNKNOWN
Requires-Dist: click (>=7)
Requires-Dist: pyyaml (>=5)
Requires-Dist: click-repl (>=0)
Requires-Dist: f5-sdk-python (>=0)
Requires-Dist: f5-teem (>=1)
